imgalz/__init__.py
imgalz/cfg/mapping.json
imgalz/models/__init__.py
imgalz/models/utils.py
imgalz/models/detector/__init__.py
imgalz/models/detector/yolov5.py
imgalz/models/detector/yolov8.py
imgalz/models/detector/yolov8pose.py
imgalz/models/detector/yolov8seg.py
imgalz/models/pose/__init__.py
imgalz/models/pose/heatmap/__init__.py
imgalz/models/pose/heatmap/heatmap_pose.py
imgalz/models/pose/heatmap/utils.py
imgalz/models/tracker/__init__.py
imgalz/models/tracker/byte_track/__init__.py
imgalz/models/tracker/byte_track/byte_track.py
imgalz/models/tracker/byte_track/tracker/__init__.py
imgalz/models/tracker/byte_track/tracker/basetrack.py
imgalz/models/tracker/byte_track/tracker/byte_tracker.py
imgalz/models/tracker/byte_track/tracker/kalman_filter.py
imgalz/models/tracker/byte_track/tracker/matching.py
imgalz/models/tracker/motpy/__init__.py
imgalz/models/tracker/motpy/motpy.py
imgalz/models/tracker/nor_fair/__init__.py
imgalz/models/tracker/nor_fair/norfair.py
imgalz/models/tracker/oc_sort/__init__.py
imgalz/models/tracker/oc_sort/ocsort.py
imgalz/models/tracker/oc_sort/tracker/__init__.py
imgalz/models/tracker/oc_sort/tracker/association.py
imgalz/models/tracker/oc_sort/tracker/kalmanfilter.py
imgalz/models/tracker/oc_sort/tracker/ocsort.py
imgalz/utils/__init__.py
imgalz/utils/box_ops.py
imgalz/utils/common.py
imgalz/utils/dataset_info.py
imgalz/utils/file_utils.py
imgalz/utils/image_filter.py
imgalz/utils/visualization.py
imgalz/utils/cpp/__init__.py
imgalz/utils/cpp/_hashfilter.cp39-win_amd64.pyd
imgalz/utils/cpp/_hashfilter.cpp
imgalz-0.0.9.0.dist-info/licenses/LICENSE
imgalz-0.0.9.0.dist-info/METADATA
imgalz-0.0.9.0.dist-info/WHEEL
imgalz-0.0.9.0.dist-info/top_level.txt
imgalz-0.0.9.0.dist-info/RECORD
