Metadata-Version: 2.4
Name: imgalz
Version: 0.0.9.0
Summary: A library providing lightweight tools for basic image processing and quick construction of detection-tracking pipelines.
License: MIT
Keywords: image-processing,image-filtering,onnx,YOLO
Classifier: Development Status :: 1 - Planning
Classifier: Intended Audience :: Developers
Classifier: Intended Audience :: Education
Classifier: Intended Audience :: Science/Research
Classifier: Programming Language :: Python :: 3
Classifier: Programming Language :: Python :: 3.8
Classifier: Programming Language :: Python :: 3.9
Classifier: Programming Language :: Python :: 3.10
Classifier: Programming Language :: Python :: 3.11
Classifier: Programming Language :: Python :: 3.12
Classifier: Topic :: Software Development
Classifier: Topic :: Scientific/Engineering
Classifier: Topic :: Scientific/Engineering :: Artificial Intelligence
Classifier: Topic :: Scientific/Engineering :: Image Recognition
Classifier: Operating System :: POSIX :: Linux
Classifier: Operating System :: MacOS
Classifier: Operating System :: Microsoft :: Windows
Requires-Python: >=3.8
License-File: LICENSE
Requires-Dist: opencv-python>=4.6.0
Requires-Dist: numpy>=1.22.2
Requires-Dist: imagehash
Requires-Dist: pillow
Requires-Dist: requests
Requires-Dist: tqdm
Requires-Dist: pyyaml
Requires-Dist: setuptools>=61.0
Requires-Dist: wheel
Requires-Dist: pybind11>=2.10
Provides-Extra: all
Requires-Dist: huggingface_hub; extra == "all"
Requires-Dist: norfair; extra == "all"
Requires-Dist: Motpy; extra == "all"
Requires-Dist: lap; extra == "all"
Requires-Dist: filterpy; extra == "all"
Provides-Extra: docs
Requires-Dist: sphinx; extra == "docs"
Requires-Dist: sphinx-rtd-theme; extra == "docs"
Requires-Dist: onnxruntime-gpu; extra == "docs"
Requires-Dist: norfair; extra == "docs"
Requires-Dist: Motpy; extra == "docs"
Requires-Dist: lap; extra == "docs"
Requires-Dist: filterpy; extra == "docs"
Dynamic: license-file
